cgitize/__init__.py
cgitize/bitbucket.py
cgitize/cgit.py
cgitize/config.py
cgitize/git.py
cgitize/github.py
cgitize/gitlab.py
cgitize/main.py
cgitize/repo.py
cgitize/utils.py
cgitize/version.py
cgitize-6.0.0.dist-info/licenses/LICENSE.txt
cgitize-6.0.0.dist-info/METADATA
cgitize-6.0.0.dist-info/WHEEL
cgitize-6.0.0.dist-info/entry_points.txt
cgitize-6.0.0.dist-info/top_level.txt
cgitize-6.0.0.dist-info/RECORD
