Metadata-Version: 2.4
Name: cgitize
Version: 6.0.0
Summary: Self-host your repositories using cgit
Author-email: Egor Tensin <egor@tensin.name>
License: MIT
Project-URL: Homepage, https://github.com/egor-tensin/cgitize
Project-URL: Bug Tracker, https://github.com/egor-tensin/cgitize/issues
Classifier: Development Status :: 5 - Production/Stable
Classifier: License :: OSI Approved :: MIT License
Classifier: Programming Language :: Python :: 3
Classifier: Topic :: Software Development :: Version Control :: Git
Requires-Python: >=3.9
License-File: LICENSE.txt
Requires-Dist: atlassian-python-api~=4.0
Requires-Dist: importlib-metadata~=4.0; python_version < "3.8"
Requires-Dist: PyGithub~=2.0
Requires-Dist: python-gitlab~=6.0
Requires-Dist: tomli~=1.0
Dynamic: license-file
